ciclops/SHAP_importance.py
ciclops/__init__.py
ciclops/__main__.py
ciclops/common.py
ciclops/models.py
ciclops/preprocess.py
ciclops/statistics.py
ciclops-0.0.4.dist-info/LICENSE
ciclops-0.0.4.dist-info/METADATA
ciclops-0.0.4.dist-info/WHEEL
ciclops-0.0.4.dist-info/entry_points.txt
ciclops-0.0.4.dist-info/top_level.txt
ciclops-0.0.4.dist-info/RECORD
