Metadata-Version: 2.1
Name: ciclops
Version: 0.0.4
Summary: Pipeline for building clinical outcome prediction models on training dataset and transfer learning on validation datasets.
Home-page: https://github.com/GuanLab/ciclops
Author: Elysia Chou, Hanrui Zhang, Yuanfang Guan
Author-email: elysian@umich.edu, rayezh@umich.edu, gyuanfan@umich.edu
License: UNKNOWN
Project-URL: Bug Tracker, https://github.com/GuanLab/ciclops/issues
Keywords: Bioinformatics,Transfer Learning,Machine Learning,Transcriptomics,Research,Clinical Outcome Prediction
Platform: UNKNOWN
Classifier: Programming Language :: Python :: 3
Classifier: License :: OSI Approved :: MIT License
Classifier: Operating System :: OS Independent
Requires-Python: >=3.8
License-File: LICENSE
Requires-Dist: numpy (>=1.21.5)
Requires-Dist: pandas (>=1.4.1)
Requires-Dist: matplotlib (>=3.5.1)
Requires-Dist: matplotlib-venn (>=0.11.7)
Requires-Dist: scikit-learn (>=1.0.2)
Requires-Dist: scipy (>=1.8.0)
Requires-Dist: lightgbm (>=3.3.2)
Requires-Dist: shap (>=0.40.0)
Requires-Dist: xgboost (>=1.6.0)
Requires-Dist: tqdm (>=4.63.0)
